{
"product_range_defaults": {
"published": false
},
"product_defaults": {
"enabled": false
},
"products_defaults": {
"notebook_a5": {
"enabled": true
},
"journal_hardback": {
"enabled": true
},
"cushion": {
"enabled": true
}
},
"variant_defaults": {
"enabled": false
},
"variants_defaults": {
"notebook_a5_lined": {
"enabled": true,
"retail_price": "18.00"
},
"notebook_a5_graph": {
"enabled": true,
"retail_price": "18.00"
},
"journal_hardback_5x7_plain": {
"enabled": true,
"retail_price": "20.00"
},
"journal_hardback_5x7_lined": {
"enabled": true,
"retail_price": "20.00"
},
"suede_12x12_cushion": {
"enabled": true,
"retail_price": "30.00"
},
"suede_16x16_cushion": {
"enabled": true,
"retail_price": "35.00"
},
"suede_18x18_cushion": {
"enabled": true,
"retail_price": "35.00"
},
"suede_19x13_cushion": {
"enabled": true,
"retail_price": "35.00"
},
"suede_22x22_cushion": {
"enabled": true,
"retail_price": "45.00"
},
"suede_24x24_cushion": {
"enabled": true,
"retail_price": "45.00"
},
"linen_12x12_cushion": {
"enabled": true,
"retail_price": "30.00"
},
"linen_16x16_cushion": {
"enabled": true,
"retail_price": "35.00"
},
"linen_18x18_cushion": {
"enabled": true,
"retail_price": "35.00"
},
"linen_19x13_cushion": {
"enabled": true,
"retail_price": "35.00"
},
"linen_22x22_cushion": {
"enabled": true,
"retail_price": "45.00"
},
"linen_24x24_cushion": {
"enabled": true,
"retail_price": "45.00"
},
"canvas_12x12_cushion": {
"enabled": true,
"retail_price": "30.00"
},
"canvas_16x16_cushion": {
"enabled": true,
"retail_price": "35.00"
},
"canvas_18x18_cushion": {
"enabled": true,
"retail_price": "35.00"
},
"canvas_19x13_cushion": {
"enabled": true,
"retail_price": "35.00"
},
"canvas_22x22_cushion": {
"enabled": true,
"retail_price": "45.00"
},
"canvas_24x24_cushion": {
"enabled": true,
"retail_price": "45.00"
}
},
"product_ranges": [
{
"title": "The Battle of Trafalgar, 21 October 1805",
"user_image_url": "http://utils.magnoliabox.com/image/nmm/BHC0565?token=5022dc125192f0bd7fbd10b59ecd52e58aaeb5be326f12b25e4a228d5deb3b46ecab611883efcba3",
"products": [
{
"notebook_a5": {
"description": "Perfect for note taking and organising, our custom printed wire bound notebooks are ideal as travel journals, for event planning, and for work or school notes. Featuring 120 pages of quality 90gsm paper, in either ruled or graph format, and a handy document pocket for storing important notes and documents.",
"variants": {
"notebook_a5_lined": {
"images": {
"front": "http://utils.magnoliabox.com/image/nmm/BHC0565?token=5022dc125192f0bd7fbd10b59ecd52e58aaeb5be326f12b25e4a228d5deb3b46ecab611883efcba3"
}
},
"notebook_a5_graph": {
"images": {
"front": "http://utils.magnoliabox.com/image/nmm/BHC0565?token=5022dc125192f0bd7fbd10b59ecd52e58aaeb5be326f12b25e4a228d5deb3b46ecab611883efcba3"
}
}
}
}
},
{
"journal_hardback": {
"description": "Our bespoke journal books provide the perfect inspiration to chronicle, doodle, draw or write. Print your favourite image across the hardcover wrap around, and choose from either ruled, graph or blank paper. Journals have a smooth, matte finish on the exterior, and feature 64 pages (128 sides) of 90 gsm paper on the inside.",
"variants": {
"journal_hardback_5x7_plain": {
"images": {
"front": "http://utils.magnoliabox.com/image/nmm/BHC0565?token=5022dc125192f0bd7fbd10b59ecd52e58aaeb5be326f12b25e4a228d5deb3b46ecab611883efcba3"
}
},
"journal_hardback_5x7_lined": {
"images": {
"front": "http://utils.magnoliabox.com/image/nmm/BHC0565?token=5022dc125192f0bd7fbd10b59ecd52e58aaeb5be326f12b25e4a228d5deb3b46ecab611883efcba3"
}
}
}
}
},
{
"cushion": {
"description": "Cushions are a great way to style your home and add a splash of colour. Customise it yours with a choice of image and fabrics: super-soft faux suede, beach-house linen, or versatile cotton canvas... Zip-back cover for easy removal and care. Includes polyester inner cushion.",
"variants": {
"suede_12x12_cushion": {
"images": {
"front": "http://utils.magnoliabox.com/image/nmm/BHC0565?token=5022dc125192f0bd7fbd10b59ecd52e58aaeb5be326f12b25e4a228d5deb3b46ecab611883efcba3"
}
},
"suede_16x16_cushion": {
"images": {
"front": "http://utils.magnoliabox.com/image/nmm/BHC0565?token=5022dc125192f0bd7fbd10b59ecd52e58aaeb5be326f12b25e4a228d5deb3b46ecab611883efcba3"
}
},
"suede_18x18_cushion": {
"images": {
"front": "http://utils.magnoliabox.com/image/nmm/BHC0565?token=5022dc125192f0bd7fbd10b59ecd52e58aaeb5be326f12b25e4a228d5deb3b46ecab611883efcba3"
}
},
"suede_19x13_cushion": {
"images": {
"front": "http://utils.magnoliabox.com/image/nmm/BHC0565?token=5022dc125192f0bd7fbd10b59ecd52e58aaeb5be326f12b25e4a228d5deb3b46ecab611883efcba3"
}
},
"suede_22x22_cushion": {
"images": {
"front": "http://utils.magnoliabox.com/image/nmm/BHC0565?token=5022dc125192f0bd7fbd10b59ecd52e58aaeb5be326f12b25e4a228d5deb3b46ecab611883efcba3"
}
},
"suede_24x24_cushion": {
"images": {
"front": "http://utils.magnoliabox.com/image/nmm/BHC0565?token=5022dc125192f0bd7fbd10b59ecd52e58aaeb5be326f12b25e4a228d5deb3b46ecab611883efcba3"
}
},
"linen_12x12_cushion": {
"images": {
"front": "http://utils.magnoliabox.com/image/nmm/BHC0565?token=5022dc125192f0bd7fbd10b59ecd52e58aaeb5be326f12b25e4a228d5deb3b46ecab611883efcba3"
}
},
"linen_16x16_cushion": {
"images": {
"front": "http://utils.magnoliabox.com/image/nmm/BHC0565?token=5022dc125192f0bd7fbd10b59ecd52e58aaeb5be326f12b25e4a228d5deb3b46ecab611883efcba3"
}
},
"linen_18x18_cushion": {
"images": {
"front": "http://utils.magnoliabox.com/image/nmm/BHC0565?token=5022dc125192f0bd7fbd10b59ecd52e58aaeb5be326f12b25e4a228d5deb3b46ecab611883efcba3"
}
},
"linen_19x13_cushion": {
"images": {
"front": "http://utils.magnoliabox.com/image/nmm/BHC0565?token=5022dc125192f0bd7fbd10b59ecd52e58aaeb5be326f12b25e4a228d5deb3b46ecab611883efcba3"
}
},
"linen_22x22_cushion": {
"images": {
"front": "http://utils.magnoliabox.com/image/nmm/BHC0565?token=5022dc125192f0bd7fbd10b59ecd52e58aaeb5be326f12b25e4a228d5deb3b46ecab611883efcba3"
}
},
"linen_24x24_cushion": {
"images": {
"front": "http://utils.magnoliabox.com/image/nmm/BHC0565?token=5022dc125192f0bd7fbd10b59ecd52e58aaeb5be326f12b25e4a228d5deb3b46ecab611883efcba3"
}
},
"canvas_12x12_cushion": {
"images": {
"front": "http://utils.magnoliabox.com/image/nmm/BHC0565?token=5022dc125192f0bd7fbd10b59ecd52e58aaeb5be326f12b25e4a228d5deb3b46ecab611883efcba3"
}
},
"canvas_16x16_cushion": {
"images": {
"front": "http://utils.magnoliabox.com/image/nmm/BHC0565?token=5022dc125192f0bd7fbd10b59ecd52e58aaeb5be326f12b25e4a228d5deb3b46ecab611883efcba3"
}
},
"canvas_18x18_cushion": {
"images": {
"front": "http://utils.magnoliabox.com/image/nmm/BHC0565?token=5022dc125192f0bd7fbd10b59ecd52e58aaeb5be326f12b25e4a228d5deb3b46ecab611883efcba3"
}
},
"canvas_19x13_cushion": {
"images": {
"front": "http://utils.magnoliabox.com/image/nmm/BHC0565?token=5022dc125192f0bd7fbd10b59ecd52e58aaeb5be326f12b25e4a228d5deb3b46ecab611883efcba3"
}
},
"canvas_22x22_cushion": {
"images": {
"front": "http://utils.magnoliabox.com/image/nmm/BHC0565?token=5022dc125192f0bd7fbd10b59ecd52e58aaeb5be326f12b25e4a228d5deb3b46ecab611883efcba3"
}
},
"canvas_24x24_cushion": {
"images": {
"front": "http://utils.magnoliabox.com/image/nmm/BHC0565?token=5022dc125192f0bd7fbd10b59ecd52e58aaeb5be326f12b25e4a228d5deb3b46ecab611883efcba3"
}
}
}
}
}
]
},
{
"title": "Greenwich Hospital from the north bank of the Thames",
"user_image_url": "http://utils.magnoliabox.com/image/nmm/BHC1827?token=d3d34807d373c432e13c81b9ab5768d68aaeb5be326f12b25e4a228d5deb3b46ecab611883efcba3",
"products": [
{
"notebook_a5": {
"description": "Perfect for note taking and organising, our custom printed wire bound notebooks are ideal as travel journals, for event planning, and for work or school notes. Featuring 120 pages of quality 90gsm paper, in either ruled or graph format, and a handy document pocket for storing important notes and documents.",
"variants": {
"notebook_a5_lined": {
"images": {
"front": "http://utils.magnoliabox.com/image/nmm/BHC1827?token=d3d34807d373c432e13c81b9ab5768d68aaeb5be326f12b25e4a228d5deb3b46ecab611883efcba3"
}
},
"notebook_a5_graph": {
"images": {
"front": "http://utils.magnoliabox.com/image/nmm/BHC1827?token=d3d34807d373c432e13c81b9ab5768d68aaeb5be326f12b25e4a228d5deb3b46ecab611883efcba3"
}
}
}
}
},
{
"journal_hardback": {
"description": "Our bespoke journal books provide the perfect inspiration to chronicle, doodle, draw or write. Print your favourite image across the hardcover wrap around, and choose from either ruled, graph or blank paper. Journals have a smooth, matte finish on the exterior, and feature 64 pages (128 sides) of 90 gsm paper on the inside.",
"variants": {
"journal_hardback_5x7_plain": {
"images": {
"front": "http://utils.magnoliabox.com/image/nmm/BHC1827?token=d3d34807d373c432e13c81b9ab5768d68aaeb5be326f12b25e4a228d5deb3b46ecab611883efcba3"
}
},
"journal_hardback_5x7_lined": {
"images": {
"front": "http://utils.magnoliabox.com/image/nmm/BHC1827?token=d3d34807d373c432e13c81b9ab5768d68aaeb5be326f12b25e4a228d5deb3b46ecab611883efcba3"
}
}
}
}
},
{
"cushion": {
"description": "Cushions are a great way to style your home and add a splash of colour. Customise it yours with a choice of image and fabrics: super-soft faux suede, beach-house linen, or versatile cotton canvas... Zip-back cover for easy removal and care. Includes polyester inner cushion.",
"variants": {
"suede_12x12_cushion": {
"images": {
"front": "http://utils.magnoliabox.com/image/nmm/BHC1827?token=d3d34807d373c432e13c81b9ab5768d68aaeb5be326f12b25e4a228d5deb3b46ecab611883efcba3"
}
},
"suede_16x16_cushion": {
"images": {
"front": "http://utils.magnoliabox.com/image/nmm/BHC1827?token=d3d34807d373c432e13c81b9ab5768d68aaeb5be326f12b25e4a228d5deb3b46ecab611883efcba3"
}
},
"suede_18x18_cushion": {
"images": {
"front": "http://utils.magnoliabox.com/image/nmm/BHC1827?token=d3d34807d373c432e13c81b9ab5768d68aaeb5be326f12b25e4a228d5deb3b46ecab611883efcba3"
}
},
"suede_19x13_cushion": {
"images": {
"front": "http://utils.magnoliabox.com/image/nmm/BHC1827?token=d3d34807d373c432e13c81b9ab5768d68aaeb5be326f12b25e4a228d5deb3b46ecab611883efcba3"
}
},
"suede_22x22_cushion": {
"images": {
"front": "http://utils.magnoliabox.com/image/nmm/BHC1827?token=d3d34807d373c432e13c81b9ab5768d68aaeb5be326f12b25e4a228d5deb3b46ecab611883efcba3"
}
},
"suede_24x24_cushion": {
"images": {
"front": "http://utils.magnoliabox.com/image/nmm/BHC1827?token=d3d34807d373c432e13c81b9ab5768d68aaeb5be326f12b25e4a228d5deb3b46ecab611883efcba3"
}
},
"linen_12x12_cushion": {
"images": {
"front": "http://utils.magnoliabox.com/image/nmm/BHC1827?token=d3d34807d373c432e13c81b9ab5768d68aaeb5be326f12b25e4a228d5deb3b46ecab611883efcba3"
}
},
"linen_16x16_cushion": {
"images": {
"front": "http://utils.magnoliabox.com/image/nmm/BHC1827?token=d3d34807d373c432e13c81b9ab5768d68aaeb5be326f12b25e4a228d5deb3b46ecab611883efcba3"
}
},
"linen_18x18_cushion": {
"images": {
"front": "http://utils.magnoliabox.com/image/nmm/BHC1827?token=d3d34807d373c432e13c81b9ab5768d68aaeb5be326f12b25e4a228d5deb3b46ecab611883efcba3"
}
},
"linen_19x13_cushion": {
"images": {
"front": "http://utils.magnoliabox.com/image/nmm/BHC1827?token=d3d34807d373c432e13c81b9ab5768d68aaeb5be326f12b25e4a228d5deb3b46ecab611883efcba3"
}
},
"linen_22x22_cushion": {
"images": {
"front": "http://utils.magnoliabox.com/image/nmm/BHC1827?token=d3d34807d373c432e13c81b9ab5768d68aaeb5be326f12b25e4a228d5deb3b46ecab611883efcba3"
}
},
"linen_24x24_cushion": {
"images": {
"front": "http://utils.magnoliabox.com/image/nmm/BHC1827?token=d3d34807d373c432e13c81b9ab5768d68aaeb5be326f12b25e4a228d5deb3b46ecab611883efcba3"
}
},
"canvas_12x12_cushion": {
"images": {
"front": "http://utils.magnoliabox.com/image/nmm/BHC1827?token=d3d34807d373c432e13c81b9ab5768d68aaeb5be326f12b25e4a228d5deb3b46ecab611883efcba3"
}
},
"canvas_16x16_cushion": {
"images": {
"front": "http://utils.magnoliabox.com/image/nmm/BHC1827?token=d3d34807d373c432e13c81b9ab5768d68aaeb5be326f12b25e4a228d5deb3b46ecab611883efcba3"
}
},
"canvas_18x18_cushion": {
"images": {
"front": "http://utils.magnoliabox.com/image/nmm/BHC1827?token=d3d34807d373c432e13c81b9ab5768d68aaeb5be326f12b25e4a228d5deb3b46ecab611883efcba3"
}
},
"canvas_19x13_cushion": {
"images": {
"front": "http://utils.magnoliabox.com/image/nmm/BHC1827?token=d3d34807d373c432e13c81b9ab5768d68aaeb5be326f12b25e4a228d5deb3b46ecab611883efcba3"
}
},
"canvas_22x22_cushion": {
"images": {
"front": "http://utils.magnoliabox.com/image/nmm/BHC1827?token=d3d34807d373c432e13c81b9ab5768d68aaeb5be326f12b25e4a228d5deb3b46ecab611883efcba3"
}
},
"canvas_24x24_cushion": {
"images": {
"front": "http://utils.magnoliabox.com/image/nmm/BHC1827?token=d3d34807d373c432e13c81b9ab5768d68aaeb5be326f12b25e4a228d5deb3b46ecab611883efcba3"
}
}
}
}
}
]
}
]
}
